xprec/__init__.py
xprec/_dd_ufunc.cpython-36m-x86_64-linux-gnu.so
xprec/linalg.py
xprec/_dd_linalg.cpython-36m-x86_64-linux-gnu.so
xprec-1.1.1.dist-info/RECORD
xprec-1.1.1.dist-info/top_level.txt
xprec-1.1.1.dist-info/LICENSE.txt
xprec-1.1.1.dist-info/METADATA
xprec-1.1.1.dist-info/WHEEL
xprec.libs/libgomp-a34b3233.so.1.0.0
