Metadata-Version: 2.1
Name: xprec
Version: 1.1.1
Summary: xprec precision numpy extension
Home-page: https://github.com/tuwien-cms/xprec
Author: Markus Wallerberger
Author-email: markus.wallerberger@tuwien.ac.at
License: UNKNOWN
Keywords: double-double
Platform: UNKNOWN
Classifier: Development Status :: 4 - Beta
Classifier: Intended Audience :: Science/Research
Classifier: Intended Audience :: Developers
Classifier: Programming Language :: Python :: 3
Requires-Python: >=3
License-File: LICENSE.txt
Requires-Dist: numpy (>=1.16)
Provides-Extra: test
Requires-Dist: pytest ; extra == 'test'
